{
   "type": "postgres",
   "host": "localhost",
   "port": 5432,
   "username": "postgres",
   "password": "postgres",
   "database": "postgres",
   "synchronize": true,
   "logging": false,
   "entities": [
      "src/app/models/**/*.ts"
   ],
   "migrations": [
      "src/database/migrations/**/*.ts"
   ],
   "subscribers": [
      "src/subscriber/**/*.ts"
   ],
   "cli": {
      "entitiesDir": "src/app/models",
      "migrationsDir": "src/database/migrations",
      "subscribersDir": "src/subscriber"
   }
}